[
  {
    "given_name": "Evan",
    "family_name": "Keel",
    "cars": [
      "MORGAN-AEROC"
    ]
  },
  {
    "given_name": "Jo",
    "family_name": "Kerr",
    "cars": [
      "TESLA-TRUCK",
      "KTM-XBOWR",
      "BMW-2"
    ]
  },
  {
    "given_name": "Izzy",
    "family_name": "Kidding",
    "cars": [
      "VW-POLO",
      "MG-MGZS",
      "ARIEL-ATOM4",
      "TESLA-MODS",
      "MG-MGZS",
      "AUDI-S8"
    ]
  },
  {
    "given_name": "Fay",
    "family_name": "King",
    "cars": []
  },
  {
    "given_name": "Joe",
    "family_name": "King",
    "cars": [
      "MORGAN-ROADSTER",
      "AUDI-S8",
      "TESLA-MOD3",
      "MINI-CONV",
      "ARIEL-ATOM4",
      "KTM-XBOWR",
      "AUDI-TT",
      "ARIEL-ATOM4",
      "MOGAN-44",
      "TESLA-MODY"
    ]
  },
  {
    "given_name": "Raney",
    "family_name": "Schauer",
    "cars": [
      "MINI-5DH",
      "AUDI-S8"
    ]
  },
  {
    "given_name": "June",
    "family_name": "Schauer",
    "cars": [
      "BMW-M6",
      "TESLA-MODX",
      "AUDI-A8",
      "TESLA-MODX",
      "BMW-2",
      "VW-ARTEON"
    ]
  },
  {
    "given_name": "April",
    "family_name": "Schauer",
    "cars": [
      "VW-POLO",
      "BMW-8",
      "TESLA-MODS",
      "BMW-1",
      "MG-HS",
      "MINI-CONV",
      "AUDI-A1",
      "MINI-CLUB",
      "ARIEL-ATOM4"
    ]
  },
  {
    "given_name": "Al K.",
    "family_name": "Seltzer",
    "cars": [
      "AUDI-A8",
      "MINI-CONV",
      "VW-AMAROK",
      "VW-ARTEON",
      "MORGAN-ROADSTER",
      "MORGAN-ROADSTER"
    ]
  },
  {
    "given_name": "Dee",
    "family_name": "Sember",
    "cars": [
      "TESLA-MOD3",
      "MG-MG3",
      "BMW-8",
      "VW-GOLF"
    ]
  },
  {
    "given_name": "Justin",
    "family_name": "Tune",
    "cars": [
      "MOGAN-44",
      "TESLA-MODY",
      "MOGAN-44"
    ]
  },
  {
    "given_name": "Carrie A.",
    "family_name": "Tune",
    "cars": [
      "BMW-8",
      "VW-ARTEON",
      "TESLA-MODX",
      "BMW-2"
    ]
  },
  {
    "given_name": "Quinn",
    "family_name": "Tuplets",
    "cars": [
      "ARIEL-ATOM4",
      "MINI-CONV",
      "BMW-M",
      "ARIEL-ATOM4",
      "AUDI-S8",
      "KTM-XBOWR",
      "TESLA-MODS"
    ]
  },
  {
    "given_name": "Colin",
    "family_name": "Allcars",
    "cars": [
      "AUDI-A1",
      "MINI-CONV",
      "BMW-M",
      "MG-MG3",
      "MG-HS",
      "VW-GOLF",
      "VW-POLO",
      "AUDI-EGT",
      "TESLA-TRUCK"
    ]
  },
  {
    "given_name": "Cary",
    "family_name": "Baggs",
    "cars": [
      "MINI-3DH",
      "MINI-3DH",
      "AUDI-S8",
      "TESLA-MODS",
      "AUDI-A8",
      "MG-MGZS",
      "BMW-1"
    ]
  },
  {
    "given_name": "Winnie",
    "family_name": "Bago",
    "cars": []
  },
  {
    "given_name": "Frank N.",
    "family_name": "Beans",
    "cars": [
      "MG-MGZS"
    ]
  },
  {
    "given_name": "Harry",
    "family_name": "Beard",
    "cars": [
      "BMW-M",
      "BMW-M",
      "MG-MGZS",
      "TESLA-MODY",
      "VW-POLO",
      "MG-HS",
      "VW-GOLF",
      "ARIEL-ATOM4",
      "MG-MGZS",
      "BMW-M2"
    ]
  },
  {
    "given_name": "Al B.",
    "family_name": "Zienya",
    "cars": [
      "TESLA-MOD3",
      "AUDI-EGT",
      "MORGAN-ROADSTER",
      "TESLA-TRUCK",
      "ARIEL-ATOM4",
      "MINI-COOPER",
      "MINI-CONV",
      "MG-MGZS"
    ]
  },
  {
    "given_name": "Cy",
    "family_name": "Yonarra",
    "cars": [
      "MINI-CLUB",
      "BMW-M2",
      "TESLA-TRUCK",
      "MINI-CONV",
      "TESLA-MOD3",
      "TESLA-TRUCK",
      "TESLA-MODX"
    ]
  },
  {
    "given_name": "Pearl E.",
    "family_name": "White",
    "cars": [
      "KTM-XBOWR",
      "BMW-M2",
      "MINI-CONV",
      "VW-ARTEON",
      "AUDI-A8",
      "TESLA-TRUCK"
    ]
  },
  {
    "given_name": "Sno",
    "family_name": "White",
    "cars": [
      "AUDI-A1",
      "TESLA-MOD3",
      "TESLA-MODX",
      "AUDI-A8"
    ]
  },
  {
    "given_name": "Chuck",
    "family_name": "Wagon",
    "cars": [
      "TESLA-MODX",
      "ARIEL-ATOM4",
      "AUDI-S8",
      "TESLA-MOD3",
      "MINI-COOPER",
      "VW-POLO",
      "VW-GOLF",
      "BMW-M2",
      "MINI-CLUB"
    ]
  },
  {
    "given_name": "Patty",
    "family_name": "Wagon",
    "cars": [
      "BMW-M2",
      "MOGAN-44",
      "MG-MGZS",
      "MINI-5DH"
    ]
  },
  {
    "given_name": "Cara",
    "family_name": "Van",
    "cars": [
      "MORGAN-AEROC"
    ]
  }
]
